Workbook

Sheet Suivis et pilotage
B3: Prestation | C3: Coût HT | D3: TVA (20%) | E3: Coût TTC | F3: Prestataire
F4: ECO-COMPENSATION | G4: SIMETHIS | H4: CERAG
A5: Pilotage et coordination | B5: Coordination de l'équipe projet et des entreprises travaux | C5: =F5+G5 -> 975 | D5: =C5*0.2 -> 195 | E5: =C5+D5 -> 1170 | F5: 975 | G5: 0 | H5: 0
B6: Interface avec les services de l'état pour le compte de la SAS BEOLETTO | C6: =F6+G6 -> 150 | D6: =C6*0.2 -> 30 | E6: =C6+D6 -> 180 | F6: 150 | G6: 0 | H6: 0
B7: Bilan annuel incluant un CR (fiche synthèse avec tableau de bord ) | C7: =F7+G7 -> 1300 | D7: =C7*0.2 -> 260 | E7: =C7+D7 -> 1560 | F7: 1300 | G7: 0 | H7: 0
B9: Sous-total pour 1 campagne | C9: =SUM(C5:C7) -> 2425 | D9: =SUM(D5:D7) -> 485 | E9: =SUM(E5:E7) -> 2910 | F9: =SUM(F5:F7) -> 2425 | G9: =SUM(G5:G7) -> 0 | H9: =SUM(H5:H7) -> 0
B11: Total pour les 11 campagnes | C11: =C9*11 -> 26675 | D11: =D9*11 -> 5335 | E11: =E9*11 -> 32010 | F11: =F9*11 -> 26675 | G11: =G9*11 -> 0 | H11: =H9*11 -> 0
B13: Prestation | C13: Coût HT | D13: TVA (20%) | E13: Coût TTC | F13: Prestataire
F14: ECO-COMPENSATION | G14: SIMETHIS | H14: CERAG
A15: Pilotage et coordination (hors période de suivi) | B15: Coordination de l'équipe projet et des entreprises travaux | C15: =F15+G15 -> 975 | D15: =C15*0.2 -> 195 | E15: =C15+D15 -> 1170 | F15: 975 | G15: 0 | H15: 0
B16: Interface avec les services de l'état pour le compte de la SAS BEOLETTO | C16: =F16+G16 -> 150 | D16: =C16*0.2 -> 30 | E16: =C16+D16 -> 180 | F16: 150 | G16: 0 | H16: 0
B18: Sous-total pour 1 campagne | C18: =SUM(C15:C16) -> 1125 | D18: =SUM(D15:D16) -> 225 | E18: =SUM(E15:E16) -> 1350 | F18: =SUM(F15:F16) -> 1125 | G18: =SUM(G15:G16) -> 0 | H18: =SUM(H15:H16) -> 0
B20: Total pour les 20 campagnes | C20: =C18*20 -> 22500 | D20: =D18*20 -> 4500 | E20: =E18*20 -> 27000 | F20: =F18*20 -> 22500 | G20: =G18*20 -> 0 | H20: =H18*20 -> 0
B23: Prestation | C23: Coût HT | D23: TVA (20%) | E23: Coût TTC | F23: Prestataire
F24: ECO-COMPENSATION | G24: SIMETHIS | H24: CERAG
A25: Encadrement écologique des opérations de génie ecogiques (Travaux uniques et d'entretien) | B25: Suivi écologique des travaux de génie écologique incluant un CR (13 demies-journées) | C25: =F25+G25 -> 975 | D25: =C25*0.2 -> 195 | E25: =C25+D25 -> 1170 | F25: 0 | G25: 975 | H25: 0
B27: Sous-total pour 1 campagne | C27: =SUM(C25:C25) -> 975 | D27: =SUM(D25:D25) -> 195 | E27: =SUM(E25:E25) -> 1170 | F27: =SUM(F25:F25) -> 0 | G27: =SUM(G25:G25) -> 975 | H27: =SUM(H25:H25) -> 0
B29: Total pour les 13 campagnes | C29: =C27*13 -> 12675 | D29: =D27*13 -> 2535 | E29: =E27*13 -> 15210 | F29: =F27*13 -> 0 | G29: =G27*13 -> 12675 | H29: =H27*13 -> 0
B31: Prestation | C31: Coût HT | D31: TVA (20%) | E31: Coût TTC | F31: Prestataire
F32: ECO-COMPENSATION | G32: SIMETHIS | H32: CERAG
A33: Mises à jour du plan par période de 5 ans | B33: Mise à jour du plan de gestion | C33: =SUM(F33:H33) -> 4100 | D33: =C33*0.2 -> 820 | E33: =SUM(C33:D33) -> 4920 | F33: 1300 | G33: 1300 | H33: 1500
B35: Total pour 1 campagne | C35: =SUM(C33:C33) -> 4100 | D35: =SUM(D33:D33) -> 820 | E35: =SUM(E33:E33) -> 4920 | F35: =SUM(F33:F33) -> 1300 | G35: =SUM(G33:G33) -> 1300 | H35: =SUM(H33:H33) -> 1500
B37: Prestation | C37: Coût HT | D37: TVA (20%) | E37: Coût TTC | F37: Prestataire
F38: ECO-COMPENSATION | G38: SIMETHIS | H38: CERAG
A39: Etat initial et suivis écologiques de l'espace de compensation | B39: Suivi amphibiens (1 passage nocturne) | C39: =SUM(F39:G39) -> 275 | D39: =C39*0.2 -> 55 | E39: =C39+D39 -> 330 | F39: 0 | G39: 275 | H39: 0
B40: Suivi entomofaune (2 passages) | C40: =SUM(F40:G40) -> 550 | D40: =C40*0.2 -> 110 | E40: =C40+D40 -> 660 | F40: 0 | G40: 550 | H40: 0
B41: Suivi floristique (1 passage habitats naturels et EEE) | C41: =SUM(F41:G41) -> 275 | D41: =C41*0.2 -> 55 | E41: =C41+D41 -> 330 | F41: 0 | G41: 275 | H41: 0
B42: Rédaction d'un rapport de suivi écologique de l'espace de compensation et du site projet incluant un bilan | C42: =SUM(F42:G42) -> 1950 | D42: =C42*0.2 -> 390 | E42: =C42+D42 -> 2340 | F42: 0 | G42: 1950 | H42: 0
B43: Rédaction de la fiche préparatoire à la saisie dans GéoMCE et transmission des données au format SINP après chaque campagne | C43: =SUM(F43:G43) -> 325 | D43: =C43*0.2 -> 65 | E43: =C43+D43 -> 390 | F43: 0 | G43: 325 | H43: 0
B45: Sous-total pour 1 campagne | C45: =SUM(C39:C43) -> 3375 | D45: =SUM(D39:D43) -> 675 | E45: =SUM(E39:E43) -> 4050 | F45: =SUM(F39:F43) -> 0 | G45: =SUM(G39:G43) -> 3375 | H45: =SUM(H39:H43) -> 0
B47: Total pour les 11 campagnes | C47: =C45*11 -> 37125 | D47: =D45*11 -> 7425 | E47: =E45*11 -> 44550 | F47: =F45*11 -> 0 | G47: =G45*11 -> 37125 | H47: =H45*11 -> 0
B49: Prestation | C49: Coût HT | D49: TVA (20%) | E49: Coût TTC | F49: Prestataire
F50: ECO-COMPENSATION | G50: SIMETHIS | H50: CERAG
A51: Etat initial et suivis piézométriques de la zone humide compensatoire | B51: Relevés des sondes à raison de 2 relevés par an sur les 5 premières années (N+1, N+2, N+3, N+4 et N+5) et sur les années N+10, N+15, N+20, N+25 et N+30 | C51: =SUM(F51:H51) -> 650 | D51: =C51*0.2 -> 130 | E51: =C51+D51 -> 780 | F51: 0 | G51: 0 | H51: 650
B53: Sous-total pour 1 campagne | C53: =SUM(C51) -> 650 | D53: =SUM(D51) -> 130 | E53: =SUM(E51) -> 780 | F53: =SUM(F51) -> 0 | G53: =SUM(G51) -> 0 | H53: =SUM(H51) -> 650
B55: Total pour les 11 campagnes | C55: =C53*11 -> 7150 | D55: =D53*11 -> 1430 | E55: =E53*11 -> 8580 | F55: =F53*11 -> 0 | G55: =G53*11 -> 0 | H55: =H53*11 -> 7150
B57: Prestation | C57: Coût HT | D57: TVA (20%) | E57: Coût TTC | F57: Prestataire
F58: ECO-COMPENSATION | G58: SIMETHIS | H58: CERAG
A59: Etat initial et suivis pédologiques de la zone humide compensatoire | B59: Campagnes de sondages pédologiques au droit de la zone humide compensatoire 1 campagne par an sur les 5 premières années (N+1, N+2, N+3, N+4 et N+5) puis sur les années N+10, N+15, N+20, N+25 et N+30 à la fin de l'hiver - début printemps | C59: =SUM(F59:H59) -> 800 | D59: =C59*0.2 -> 160 | E59: =C59+D59 -> 960 | F59: 0 | G59: 0 | H59: 800
B61: Sous-total pour 1 campagne | C61: =SUM(C59) -> 800 | D61: =SUM(D59) -> 160 | E61: =SUM(E59) -> 960 | F61: =SUM(F59) -> 0 | G61: =SUM(G59) -> 0 | H61: =SUM(H59) -> 800
B63: Total pour les 11 campagnes | C63: =C61*11 -> 8800 | D63: =D61*11 -> 1760 | E63: =E61*11 -> 10560 | F63: =F61*11 -> 0 | G63: =G61*11 -> 0 | H63: =H61*11 -> 8800
B65: Prestation | C65: Coût HT | D65: TVA (20%) | E65: Coût TTC | F65: Prestataire
F66: ECO-COMPENSATION | G66: SIMETHIS | H66: CERAG
A67: Etat initial et suivis piézométriques et pédologiques de la zone humide compensatoire et zone humide évitée | B67: Rédaction d'un rapport de suivis hydrogéologiques et pédologiques | C67: =SUM(F67:H67) -> 1000 | D67: =C67*0.2 -> 200 | E67: =C67+D67 -> 1200 | F67: 0 | G67: 0 | H67: 1000
B69: Sous-total pour 1 campagne | C69: =SUM(C67) -> 1000 | D69: =SUM(D67) -> 200 | E69: =SUM(E67) -> 1200 | F69: =SUM(F67) -> 0 | G69: =SUM(G67) -> 0 | H69: =SUM(H67) -> 1000
B71: Total pour les 11 campagnes | C71: =C69*11 -> 11000 | D71: =D69*11 -> 2200 | E71: =E69*11 -> 13200 | F71: =F69*11 -> 0 | G71: =G69*11 -> 0 | H71: =H69*11 -> 11000
B74: Prestation | C74: Coût HT | D74: TVA (20%) | E74: Coût TTC | F74: Prestataire
F75: ECO-COMPENSATION | G75: SIMETHIS | H75: CERAG
A76: Rédaction d'un bilan de fin des mesures compensatoires | B76: Rédaction d'un bilan de fin des mesures compensatoires | C76: =SUM(F76:H76) -> 5200 | D76: =C76*0.2 -> 1040 | E76: =SUM(C76:D76) -> 6240 | F76: 1950 | G76: 1950 | H76: 1300
B78: Total | C78: =SUM(C76) -> 5200 | D78: =SUM(D76) -> 1040 | E78: =SUM(E76) -> 6240 | F78: =SUM(F76) -> 1950 | G78: =SUM(G76) -> 1950 | H78: =SUM(H76) -> 1300
B80: TOTAL SUIVIS ECOLOGIQUES ET PILOTAGE | C80: =C20+C11+C29+C35+C47+C55+C63+C71+C78 -> 135225 | D80: =D20+D11+D29+D35+D47+D55+D63+D71+D78 -> 27045 | E80: =E20+E11+E29+E35+E47+E55+E63+E71+E78 -> 162270 | F80: =F20+F11+F29+F35+F47+F55+F63+F71+F78 -> 52425 | G80: =G20+G11+G29+G35+G47+G55+G63+G71+G78 -> 53050 | H80: =H20+H11+H29+H35+H47+H55+H63+H71+H78 -> 29750 | I80: =SUM(F80:H80) -> 135225
B82: Prestation optionnelle (à la demande de la DREAL) | C82: Coût HT | D82: TVA (20%) | E82: Coût TTC | F82: Prestataire
F83: ECO-COMPENSATION | G83: SIMETHIS | H83: CERAG
A84: Comité de suivi à l'unité | B84: Animation des comités de suivi avec les services de l'état pour le compte de la MO incluant un PWP et une participation des différents experts | C84: =SUM(F84:H84) -> 1800 | D84: =C84*0.2 -> 360 | E84: =C84+D84 -> 2160 | F84: 600 | G84: 600 | H84: 600
B85: Rédaction d'un compte-rendu à l'issue de chaque comités de suivi | C85: =SUM(F85:H85) -> 300 | D85: =C85*0.2 -> 60 | E85: =C85+D85 -> 360 | F85: 300 | G85: 0 | H85: 0
B87: Total à l'unité | C87: =SUM(C84:C85) -> 2100 | D87: =SUM(D84:D85) -> 420 | E87: =SUM(E84:E85) -> 2520 | F87: =SUM(F84:F85) -> 900 | G87: =SUM(G84:G85) -> 600 | H87: =SUM(H84:H85) -> 600

Sheet Planning
E1: Etat de référence | F1: N | G1: N+1 | H1: N+2 | I1: N+3 | J1: N+4 | K1: N+5 | L1: N+6 | M1: N+7 | N1: N+8 | O1: N+9 | P1: N+10 | Q1: N+11 | R1: N+12 | S1: N+13 | T1: N+14 | U1: N+15 | V1: N+16 | W1: N+17 | X1: N+18 | Y1: N+19 | Z1: N+20 | AA1: N+21 | AB1: N+22 | AC1: N+23 | AD1: N+24 | AE1: N+25 | AF1: N+26 | AG1: N+27 | AH1: N+28 | AI1: N+29
B2: PILOTAGE ET SUIVIS ECOLOGIQUES | D2: Code mesure | E2: 2023 | F2: 2024 | G2: 2025 | H2: 2026 | I2: 2027 | J2: 2028 | K2: 2029 | L2: 2030 | M2: 2031 | N2: 2032 | O2: 2033 | P2: 2034 | Q2: 2035 | R2: 2036 | S2: 2037 | T2: 2038 | U2: 2039 | V2: 2040 | W2: 2041 | X2: 2042 | Y2: 2043 | Z2: 2044 | AA2: 2045 | AB2: 2046 | AC2: 2047 | AD2: 2048 | AE2: 2049 | AF2: 2050 | AG2: 2051 | AH2: 2052 | AI2: 2053
B3: Pilotage et coordination | C3: Coordination de l'équipe projet et des entreprises travaux | D3: MG 1 | E3: X | F3: X | G3: X | H3: X | I3: X | J3: X | K3: X | L3: X | M3: X | N3: X | O3: X | P3: X | Q3: X | R3: X | S3: X | T3: X | U3: X | V3: X | W3: X | X3: X | Y3: X | Z3: X | AA3: X | AB3: X | AC3: X | AD3: X | AE3: X | AF3: X | AG3: X | AH3: X | AI3: X
C4: Interface avec les services de l'état pour le compte de la SAS BEOLETTO | E4: X | F4: X | G4: X | H4: X | I4: X | J4: X | K4: X | L4: X | M4: X | N4: X | O4: X | P4: X | Q4: X | R4: X | S4: X | T4: X | U4: X | V4: X | W4: X | X4: X | Y4: X | Z4: X | AA4: X | AB4: X | AC4: X | AD4: X | AE4: X | AF4: X | AG4: X | AH4: X | AI4: X
C5: Résumé non technique en fin de chaque campagne de suivi | E5: X | F5: X | G5: X | H5: X | I5: X | J5: X | K5: X | L5: X | M5: X | N5: X | O5: X | P5: X | Q5: X | R5: X | S5: X | T5: X | U5: X | V5: X | W5: X | X5: X | Y5: X | Z5: X | AA5: X | AB5: X | AC5: X | AD5: X | AE5: X | AF5: X | AG5: X | AH5: X | AI5: X
B6: Mises à jour du plan de gestion tous les 5 ans | C6: Mises à jour du plan de gestion | D6: MG 2 | E6: X | J6: X | O6: X | T6: X | Y6: X | AD6: X
B7: Encadrement écologique | C7: Encadrement écologique des opérations de génie éclogiques (travaux uniques et d'entretien) incluant un CR | D7: MG 1 | E7: 3 demies-journées | F7: 1 demie-journée | I7: 1 demie-journée | L7: 1 demie-journée | O7: 1 demie-journée | R7: 1 demie-journée | U7: 1 demie-journée | X7: 1 demie-journée | AA7: 1 demie-journée | AD7: 1 demie-journée | AG7: 1 demie-journée
B8: Etat initial et suivis écologiques de l'espace de compensation | C8: Suivi amphibiens (1 passage nocturne) | D8: SE 4 | E8: X | F8: X | G8: X | H8: X | I8: X | J8: X | O8: X | T8: X | Y8: X | AD8: X | AI8: X
C9: Suivi entomofaune (3 passages) | E9: X | F9: X | G9: X | H9: X | I9: X | J9: X | O9: X | T9: X | Y9: X | AD9: X | AI9: X
C10: Suivi floristique (1 passage habitats naturels et EEE) | E10: X | F10: X | G10: X | H10: X | I10: X | J10: X | K10: ² | O10: X | T10: X | Y10: X | AD10: X | AI10: X
C11: Rédaction d'un rapport de suivi écologique de l'espace de compensation et du site projet incluant un bilan | E11: X | F11: X | G11: X | H11: X | I11: X | J11: X | O11: X | T11: X | Y11: X | AD11: X | AI11: X
C12: Rédaction de la fiche préparatoire à la saisie dans GéoMCE et transmission des données au format SINP après chaque campagne | E12: X | F12: X | G12: X | H12: X | I12: X | J12: X | O12: X | T12: X | Y12: X | AD12: X | AI12: X
B13: Etat initial et suivis piézomériques et pédologiques de la zone humide compensatoire | C13: Relevés des sondes à raison de 2 relevés par an sur les 5 premières années puis tous les 5 ans | D13: SE 1 | E13: 2 relevés | F13: 2 relevés | G13: 2 relevés | H13: 2 relevés | I13: 2 relevés | J13: 2 relevés | O13: 2 relevés | T13: 2 relevés | Y13: 2 relevés | AD13: 2 relevés | AI13: 2 relevés
C14: Sondages pédologiques à la tarière à main | D14: SE 2 | E14: X | F14: X | G14: X | H14: X | I14: X | J14: X | O14: X | T14: X | Y14: X | AD14: X | AI14: X
C15: Rédaction d'un rapport de suivi | D15: SE 1 et SE2 | E15: X | F15: X | G15: X | H15: X | I15: X | J15: X | O15: X | T15: X | Y15: X | AD15: X | AI15: X
B16: Etat initial et suivis hydromorphologique du fossé | C16: Suivi hydromorphologique et rédaction d'un rapport de suivi | D16: SE 3 | E16: X | J16: X | O16: X | T16: X | Y16: X | AD16: X | AI16: X
B17: Rédaction d'un bilan de fin des mesures compensatoires | C17: Rédaction d'un bilan de fin des mesures compensatoires | D17: MG 2 | AI17: X
E19: Etat de référence | F19: N | G19: N+1 | H19: N+2 | I19: N+3 | J19: N+4 | K19: N+5 | L19: N+6 | M19: N+7 | N19: N+8 | O19: N+9 | P19: N+10 | Q19: N+11 | R19: N+12 | S19: N+13 | T19: N+14 | U19: N+15 | V19: N+16 | W19: N+17 | X19: N+18 | Y19: N+19 | Z19: N+20 | AA19: N+21 | AB19: N+22 | AC19: N+23 | AD19: N+24 | AE19: N+25 | AF19: N+26 | AG19: N+27 | AH19: N+28 | AI19: N+29
B20: TRAVAUX DE GENIE ECOLOGIQUE | D20: Code mesure | E20: 2023 | F20: 2024 | G20: 2025 | H20: 2026 | I20: 2027 | J20: 2028 | K20: 2029 | L20: 2030 | M20: 2031 | N20: 2032 | O20: 2033 | P20: 2034 | Q20: 2035 | R20: 2036 | S20: 2037 | T20: 2038 | U20: 2039 | V20: 2040 | W20: 2041 | X20: 2042 | Y20: 2043 | Z20: 2044 | AA20: 2045 | AB20: 2046 | AC20: 2047 | AD20: 2048 | AE20: 2049 | AF20: 2050 | AG20: 2051 | AH20: 2052 | AI20: 2053
B21: Travaux de génie écologique (travaux uniques) | C21: Pose de 2 piézomètres incluant la maintance tous les 5 ans* | D21: SE 1 | E21: X | J21: X | O21: X | T21: X | Y21: X | AD21: X | AI21: X
C22: Equipements des piézomètres avec des sondes et remplacement au bout de 10 ans | D22: SE 1 | E22: X | O22: X | Y22: X
C23: Création de 2 dépressions humides par étrépage (30 cm) - environ 2 x 200 m² | D23: TU 1 | E23: X
C24: Travaux de décapage (50 cm) sur les deux dépressions | D24: TU 1 | E24: X
C25: Travaux de décapage (50 cm) + imperméablisation argile sur les deux dépressions | D25: TU 1 | E25: X
C26: Création d'un seuil en rondins de bois (option) | D26: TU 2 | E26: Si nécéssaire à l'issue des premiers suivis
C27: Suppression et évacuation des ligneux | D27: TU 3 | E27: X
B28: Travaux de génie écologique (travaux d'entretien) | C28: Entretien des landes humides | D28: TE 1 | F28: X | I28: X | L28: X | O28: X | R28: X | U28: X | X28: X | AA28: X | AD28: X | AG28: X
E30: Etat de référence | F30: N | G30: N+1 | H30: N+2 | I30: N+3 | J30: N+4 | K30: N+5 | L30: N+6 | M30: N+7 | N30: N+8 | O30: N+9 | P30: N+10 | Q30: N+11 | R30: N+12 | S30: N+13 | T30: N+14 | U30: N+15 | V30: N+16 | W30: N+17 | X30: N+18 | Y30: N+19 | Z30: N+20 | AA30: N+21 | AB30: N+22 | AC30: N+23 | AD30: N+24 | AE30: N+25 | AF30: N+26 | AG30: N+27 | AH30: N+28 | AI30: N+29
B31: PILOTAGE ET SUIVIS ECOLOGIQUES | D31: Code mesure | E31: 2023 | F31: 2024 | G31: 2025 | H31: 2026 | I31: 2027 | J31: 2028 | K31: 2029 | L31: 2030 | M31: 2031 | N31: 2032 | O31: 2033 | P31: 2034 | Q31: 2035 | R31: 2036 | S31: 2037 | T31: 2038 | U31: 2039 | V31: 2040 | W31: 2041 | X31: 2042 | Y31: 2043 | Z31: 2044 | AA31: 2045 | AB31: 2046 | AC31: 2047 | AD31: 2048 | AE31: 2049 | AF31: 2050 | AG31: 2051 | AH31: 2052 | AI31: 2053
B32: Pilotage et coordination | C32: Coordination de l'équipe projet et des entreprises travaux | D32: MG 1 | E32: 2425 | F32: 2425 | G32: ='Suivis et pilotage'!C9 -> 2425 | H32: 2425 | I32: 2425 | J32: 2425 | K32: 1125 | L32: 1125 | M32: 1125 | N32: 1125 | O32: 2425 | P32: 1125 | Q32: 1125 | R32: 1125 | S32: 1125 | T32: 2425 | U32: 1125 | V32: 1125 | W32: 1125 | X32: 1125 | Y32: 2425 | Z32: 1125 | AA32: 1125 | AB32: 1125 | AC32: 1125 | AD32: 2425 | AE32: 1125 | AF32: 1125 | AG32: 1125 | AH32: 1125 | AI32: 2425 | AJ32: =SUM(E32:AI34) -> 49175
C33: Interface avec les services de l'état pour le compte de la SAS BEOLETTO
C34: Résumé non technique en fin de chaque campagne de suivi
B35: Mises à jour du plan de gestion tous les 5 ans | C35: Mises à jour du plan de gestion | D35: MG 2 | E35: ='Suivis et pilotage'!C35 -> 4100 | J35: Si nécéssaire | O35: Si nécéssaire | T35: Si nécéssaire | Y35: Si nécéssaire | AD35: Si nécéssaire | AJ35: =SUM(E35:AI35) -> 4100
B36: Encadrement écologique | C36: Encadrement écologique des opérations de génie éclogiques (travaux uniques et d'entretien) incluant un CR | D36: MG 1 | E36: 2925 | F36: 975 | I36: 975 | L36: 975 | O36: 975 | R36: 975 | U36: 975 | X36: 975 | AA36: 975 | AD36: 975 | AG36: 975 | AJ36: =SUM(E36:AI36) -> 12675
B37: Etat initial et suivis écologiques de l'espace de compensation | C37: Suivi amphibiens (1 passage nocturne) | D37: SE 4 | E37: 3375 | F37: 3375 | G37: 3375 | H37: 3375 | I37: 3375 | J37: 3375 | O37: 3375 | T37: 3375 | Y37: 3375 | AD37: 3375 | AI37: 3375 | AJ37: =SUM(E37:AI41) -> 37125
C38: Suivi entomofaune (3 passages)
C39: Suivi floristique (1 passage habitats naturels et EEE) | K39: ²
C40: Rédaction d'un rapport de suivi écologique de l'espace de compensation incluant un bilan
C41: Rédaction de la fiche préparatoire à la saisie dans GéoMCE et transmission des données au format SINP après chaque campagne
B42: Etat initial et suivis piézométriques, pédologiques et hydromorpholohiques de la zone humide compensatoire | C42: Relevés des sondes à raison de 2 relevés par an sur les 5 premières années puis tous les 5 ans | D42: SE 1 | E42: 2450 | F42: 2450 | G42: 2450 | H42: 2450 | I42: 2450 | J42: 2450 | O42: 2450 | T42: 2450 | Y42: 2450 | AD42: 2450 | AI42: 2450 | AJ42: =SUM(E42:AI45) -> 26950
C43: Sondages pédologiques à la tarière à main | D43: SE 2
C44: Suivi hydromorphologique | D44: SE 3
C45: Rédaction d'un rapport de suivi de l'espace de compensation incluant un bilan | D45: SE 1 et SE2
B46: Rédaction d'un bilan de fin des mesures compensatoires | C46: Rédaction d'un bilan de fin des mesures compensatoires | D46: MG 2 | AI46: 5200 | AJ46: =SUM(E46:AI46) -> 5200
E47: =SUM(E32:E46) -> 15275 | F47: =SUM(F32:F46) -> 9225 | G47: =SUM(G32:G46) -> 8250 | H47: =SUM(H32:H46) -> 8250 | I47: =SUM(I32:I46) -> 9225 | J47: =SUM(J32:J46) -> 8250 | K47: =SUM(K32:K46) -> 1125 | L47: =SUM(L32:L46) -> 2100 | ... AI47: =SUM(AI32:AI46) -> 13450 | AJ47: =SUM(E47:AI47) -> 135225 | AK47: =AJ47*0.2 -> 27045 | AL47: =AJ47+AK47 -> 162270
E48: =SUM(E47:AI47) -> 135225 | AJ48: =SUM(AJ32:AJ46) -> 135225
E50: Etat de référence | F50: N | G50: N+1 | H50: N+2 | I50: N+3 | J50: N+4 | K50: N+5 | L50: N+6 | M50: N+7 | N50: N+8 | O50: N+9 | P50: N+10 | Q50: N+11 | R50: N+12 | S50: N+13 | T50: N+14 | U50: N+15 | V50: N+16 | W50: N+17 | X50: N+18 | Y50: N+19 | Z50: N+20 | AA50: N+21 | AB50: N+22 | AC50: N+23 | AD50: N+24 | AE50: N+25 | AF50: N+26 | AG50: N+27 | AH50: N+28 | AI50: N+29
B51: TRAVAUX DE GENIE ECOLOGIQUE | D51: Code mesure | E51: 2023 | F51: 2024 | G51: 2025 | H51: 2026 | I51: 2027 | J51: 2028 | K51: 2029 | L51: 2030 | M51: 2031 | N51: 2032 | O51: 2033 | P51: 2034 | Q51: 2035 | R51: 2036 | S51: 2037 | T51: 2038 | U51: 2039 | V51: 2040 | W51: 2041 | X51: 2042 | Y51: 2043 | Z51: 2044 | AA51: 2045 | AB51: 2046 | AC51: 2047 | AD51: 2048 | AE51: 2049 | AF51: 2050 | AG51: 2051 | AH51: 2052 | AI51: 2053
B52: Travaux de génie écologique (travaux uniques) | C52: Pose de 1 piézomètres incluant la maintance tous les 5 ans et le remplacement au bout de 15 ans | D52: SE 1 | E52: 2000 | J52: 800 | O52: 800 | T52: 2000 | Y52: 800 | AD52: 800 | AJ52: =SUM(E52:AI52) -> 7200
C53: Equipements des piézomètres avec des sondes et remplacement au bout de 10 ans | D53: SE 1 | E53: 1400 | O53: 1400 | Y53: 1400 | AJ53: =SUM(E53:AI53) -> 4200
C54: Installation et repli de chantier inlaunt la mise en place d'un grillage à mouton | D54: - | E54: 9200
C55: Création de 2 dépressions humides par étrépage (50 cm) - environ 2 x 200 m² | D55: TU 1 | E55: 5500
C56: Création d'un seuil en rondins de bois | D56: TU 2 | E56: 1775
C57: Suppression et évacuation des ligneux | D57: TU 3 | E57: 4200
B58: Travaux de génie écologique (travaux d'entretien) | C58: Entretien des landes humides | D58: TE 1 | E58: 1575 | I58: 2050 | L58: 2050 | O58: 2050 | R58: 2050 | U58: 2050 | X58: 2050 | AA58: 2050 | AD58: 2050 | AG58: 2050
E59: =SUM(E52:E58) -> 25650 | F59: =SUM(F52:F58) -> 0 | G59: =SUM(G52:G58) -> 0 | H59: =SUM(H52:H58) -> 0 | I59: =SUM(I52:I58) -> 2050 | J59: =SUM(J52:J58) -> 800 | K59: =SUM(K52:K58) -> 0 | L59: =SUM(L52:L58) -> 2050 | ... AI59: =SUM(AI52:AI58) -> 0 | AJ59: =SUM(E59:AI59) -> 52100
E60: =SUM(E59:AI59) -> 52100
B62: TOTAL ESTIMATIF HORS TAXES PAR AN | E62: =E47+E59 -> 40925 | F62: =SUM(F47+F59) -> 9225 | G62: =SUM(G47+G59) -> 8250 | H62: =SUM(H47+H59) -> 8250 | I62: =SUM(I47+I59) -> 11275 | J62: =SUM(J47+J59) -> 9050 | K62: =SUM(K47+K59) -> 1125 | L62: =SUM(L47+L59) -> 4150 | M62: =SUM(M47+M59) -> 1125 | ... AI62: =SUM(AI47+AI59) -> 13450
B63: TOTAL ESTIMATIF HORS TAXES PAR AN (incluant un aléas 20 % sur 25 dernières années) | E63: - | F63: - | G63: - | H63: - | I63: - | J63: - | K63: =K62+K62*0.2 -> 1350 | L63: =L62+L62*0.2 -> 4980 | M63: =M62+M62*0.2 -> 1350 | N63: =N62+N62*0.2 -> 1350 | O63: =O62+O62*0.2 -> 16170 | P63: =P62+P62*0.2 -> 1350 | Q63: =Q62+Q62*0.2 -> 1350 | R63: =R62+R62*0.2 -> 4980 | ... AI63: =AI62+AI62*0.2 -> 16140
B64: TOTAL ESTIMATIF HORS TAXES PAR 31 ANS | E64: =SUM(E62:J62) -> 86975 | K64: =SUM(K63:AI63) -> 120420 | AJ64: =SUM(E64:AI64) -> 207395
B65: TOTAL ESTIMATIFTOUTES TAXES COMPRISES TAXES PAR 31 ANS (TVA 20 %) | E65: =E64*0.2+E64 -> 104370 | K65: =K64*0.2+K64 -> 144504 | AJ65: =SUM(E65:AI65) -> 248874
B66: ECO-COMPENSATION | E66: =E32+1300 -> 3725 | F66: =F32 -> 2425 | G66: =G32 -> 2425 | H66: =H32 -> 2425 | I66: =I32 -> 2425 | J66: =J32 -> 2425 | K66: =K32 -> 1125 | L66: =L32 -> 1125 | M66: =M32 -> 1125 | ... AH66: =AH32 -> 1125 | AI66: =AI32+1950 -> 4375 | AJ66: =SUM(E66:AI66) -> 52425
B67: SIMETHIS | E67: =E37+E36+1300 -> 7600 | F67: =F37+F36 -> 4350 | G67: =G37+G36 -> 3375 | H67: =H37+H36 -> 3375 | I67: =I37+I36 -> 4350 | J67: =J37+J36 -> 3375 | K67: =K37+K36 -> 0 | L67: =L37+L36 -> 975 | M67: =M37+M36 -> 0 | ... AH67: =AH37+AH36 -> 0 | AI67: =AI37+AI36+1950 -> 5325 | AJ67: =SUM(E67:AI67) -> 53050
B68: CERAG | E68: =E42+E52+E53+1500 -> 7350 | F68: =F42+F52+F53 -> 2450 | G68: =G42+G52+G53 -> 2450 | H68: =H42+H52+H53 -> 2450 | I68: =I42+I52+I53 -> 2450 | J68: =J42+J52+J53 -> 3250 | K68: =K42+K52+K53 -> 0 | L68: =L42+L52+L53 -> 0 | M68: =M42+M52+M53 -> 0 | ... AH68: =AH42+AH52+AH53 -> 0 | AI68: =AI42+AI52+AI53+1300 -> 3750 | AJ68: =SUM(E68:AI68) -> 41150
B69: EGAN AQUITAINE | E69: =SUM(E55:E58) -> 13050 | F69: =SUM(F55:F58) -> 0 | G69: =SUM(G55:G58) -> 0 | H69: =SUM(H55:H58) -> 0 | I69: =SUM(I55:I58) -> 2050 | J69: =SUM(J55:J58) -> 0 | K69: =SUM(K55:K58) -> 0 | L69: =SUM(L55:L58) -> 2050 | ... AI69: =SUM(AI55:AI58) -> 0 | AJ69: =SUM(E69:AI69) -> 31500
E70: =SUM(E66:E69) -> 31725 | F70: =SUM(F66:F69) -> 9225 | G70: =SUM(G66:G69) -> 8250 | H70: =SUM(H66:H69) -> 8250 | I70: =SUM(I66:I69) -> 11275 | J70: =SUM(J66:J69) -> 9050 | K70: =SUM(K66:K69) -> 1125 | L70: =SUM(L66:L69) -> 4150 | ... AI70: =SUM(AI66:AI69) -> 13450 | AJ70: =SUM(E70:AI70) -> 178125
B72: TOTAL HT ECO/SIMETHIS/CERAG | E72: =E66+E67+E68 -> 18675 | F72: =F66+F67+F68 -> 9225 | G72: =G66+G67+G68 -> 8250 | H72: =H66+H67+H68 -> 8250 | I72: =I66+I67+I68 -> 9225 | J72: =J66+J67+J68 -> 9050 | K72: =K66+K67+K68 -> 1125 | L72: =L66+L67+L68 -> 2100 | ... AI72: =AI66+AI67+AI68 -> 13450 | AJ72: =SUM(E72:AI72) -> 146625
B73: Acompte de 30 % HT | E73: =E72*0.3 -> 5602.5 | F73: =F72*0.3 -> 2767.5 | G73: =G72*0.3 -> 2475 | H73: =H72*0.3 -> 2475 | I73: =I72*0.3 -> 2767.5 | J73: =J72*0.3 -> 2715 | K73: =K72*0.3 -> 337.5 | L73: =L72*0.3 -> 630 | ... AI73: =AI72*0.3 -> 4035 | AJ73: =SUM(E73:AI73) -> 43987.5
B74: Solde 70 % HT | E74: =E72*0.7 -> 13072.5 | F74: =F72*0.7 -> 6457.5 | G74: =G72*0.7 -> 5775 | H74: =H72*0.7 -> 5775 | I74: =I72*0.7 -> 6457.5 | J74: =J72*0.7 -> 6335 | K74: =K72*0.7 -> 787.5 | L74: =L72*0.7 -> 1470 | ... AI74: =AI72*0.7 -> 9415 | AJ74: =SUM(E74:AI74) -> 102637.5

Sheet DECOMPTE 2023
A3: 33689 - DECOMPTE GENERAL ANNEE 2023
A5: STRUCTURE | B5: PRESTATION | C5: MONTANT DU MARCHE HT | D5: DEJA FACTURE | E5: DONT PREMIER ACOMPTE HT | F5: DONT DEUXIEME ACOMPTE HT | G5: DONT TROISIEME ACOMPTE HT | H5: QUATRIEME ACOMPTE HT | I5: COMMENTAIRES
A6: ECO-COMPENSATION | B6: Pilotage et coordination | C6: =Planning!E32 -> 2425 | D6: =C6*0.3 -> 727.5 | E6: 727.5 | F6: 0 | G6: 0 | H6: =C6-E6 -> 1697.5 | I6: -
B7: Mise à jour du plan de gestion | C7: 1300 | D7: =C7*0.3 -> 390 | E7: 390 | F7: 0 | G7: 0 | H7: =C7-E7 -> 910 | I7: -
A8: ECO-COMPENSATION | C8: =SUM(C6:C7) -> 3725 | D8: =C8*0.3 -> 1117.5 | E8: 1117.5 | F8: =SUM(F6:F7) -> 0 | G8: =SUM(G6:G7) -> 0 | H8: =SUM(H6:H7) -> 2607.5 | I8: -
A9: SIMETHIS (SOUS-TRAITANT) | B9: Mise à jour du plan de gestion | C9: 1300 | D9: =C9*0.3 -> 390 | E9: 390 | F9: 0 | G9: 0 | H9: =-E9 -> -390 | I9: Prestation non réalisée (-1 300,00 €)
B10: Encadrement écologique | C10: =Planning!E36 -> 2925 | D10: =C10*0.3 -> 877.5 | E10: 877.5 | F10: 0 | G10: 0 | H10: =C10-D10 -> 2047.5 | I10: -
B11: Etat initial et suivis écologiques de l'espace de compensation | C11: =Planning!E37 -> 3375 | D11: =C11*0.3 -> 1012.5 | E11: 1012.5 | F11: 0 | G11: 0 | H11: =C11-E11 -> 2362.5 | I11: -
A12: SIMETHIS (SOUS-TRAITANT) | C12: =SUM(C9:C11) -> 7600 | D12: =C12*0.3 -> 2280 | E12: 2280 | F12: 0 | G12: 0 | H12: =SUM(H9:H11) -> 4020 | I12: -
A13: CERAG (SOUS-TRAITANT) | B13: Mise à jour du plan de gestion | C13: 1500 | D13: =C13*0.3 -> 450 | E13: 450 | F13: 0 | G13: 0 | H13: -450 | I13: Prestation non réalisée (-1 500,00 €)
B14: Etat initial et suivis piézométriques, pédologiques et hydromorpholohiques de la zone humide compensatoire | C14: =Planning!E42 -> 2450 | D14: =C14*0.3 -> 735 | E14: 735 | F14: 0 | G14: 0 | H14: =C14-E14 -> 1715 | I14: -
B15: Pose et équipement du piézomètre | C15: 3400 | D15: =C15*0.3 -> 1020 | E15: 1020 | F15: 0 | G15: 0 | H15: =C15-D15 -> 2380 | I15: -
A16: CERAG (SOUS-TRAITANT) | C16: =SUM(C13:C15) -> 7350 | D16: =C16*0.3 -> 2205 | E16: 2205 | F16: 0 | G16: 0 | H16: =SUM(H13:H15) -> 3645 | I16: -
A17: FACTURATION ECO-COMPENSATION | C17: =C8+C12+C16 -> 18675 | D17: =SUM(D8+D12+D16) -> 5602.5 | E17: =E8+E12+E16 -> 5602.5 | F17: =F8+F12+F16 -> 0 | G17: 0 | H17: =SUM(H16+H12+H8) -> 10272.5
A19: EGAN Aquitaine (CO-TRAITANT) | B19: Installation et repli de chantier inlaunt la mise en place d'un grillage à mouton | C19: 3200 | D19: =E19+F19 -> 3200 | E19: 1600 | F19: =C19*0.5 -> 1600 | G19: 0 | H19: 0 | I19: 0
B20: Mise en place d'une clôture en grillage à mouton avec piquets bois - 200 ml | C20: 6000 | D20: =E20+F20 -> 6000 | E20: 6000 | F20: 0 | G20: 0 | H20: 0 | I20: 0
B21: Création de 2 dépressions humides par étrépage (50 cm) - environ 2 x 200 m² | C21: 5500 | D21: =E21+F21 -> 5500 | E21: 1650 | F21: =C21*0.7 -> 3850 | G21: 0 | H21: 0 | I21: 0
B22: Création d'un seuil en rondins de bois | C22: 1775 | D22: 0 | E22: 0 | F22: 0 | G22: 0 | H22: 0 | I22: Prestation non réalisée (-1 775,00 €)
B23: Suppression et évacuation des ligneux | C23: 4200 | D23: =E23+F23+G23 -> 4200 | E23: 0 | F23: =C23*0.3 -> 1260 | G23: =C23-F23 -> 2940 | H23: 0 | I23: 0
B24: Entretien des landes humides | C24: 1575 | D24: =E24+F24+G24 -> 1575 | E24: 0 | F24: =C24*0.3 -> 472.5 | G24: =C24-F24 -> 1102.5 | H24: 0 | I24: 0
A25: FACTURATION EGAN Aquitaine | C25: =SUM(C19:C24) -> 22250 | D25: =SUM(D19:D24)-D22 -> 20475 | E25: =SUM(E19:E24)-E22 -> 9250 | F25: =SUM(F19:F24)-F22 -> 7182.5 | G25: =SUM(G19:G24)-G22 -> 4042.5 | H25: 0 | I25: 0
A27: TOTAL ANNEE 2023 | C27: MONTANT DU MARCHE HT | E27: TOTAL DÉJÀ FACTURE HT | F27: TOTAL DÉJÀ FACTURE HT | G27: TOTAL DÉJÀ FACTURE HT | H27: TOTAL ACOMPTE A PAYER HT | I27: RESTANT A FACTURER TTC
A28: PREVISONNEL 2023 | C28: =C25+C17 -> 40925
A29: FIN DE MISSION 2023 | C29: =C25+C17-C9-C13-C22 -> 36350 | E29: =E17+E25 -> 14852.5 | F29: =F25 -> 7182.5 | G29: =G25 -> 4042.5 | H29: 10272.5 | I29: =(C29*1.2)-(E29*1.2)-(F29*1.2)-(G29*1.2)-(H29*1.2) -> 0
A31: Eco-Compensation : PREVISONNEL 2023 | C31: =C17 -> 18675
A32: Eco-Compensation : FIN DE MISSION 2023 | C32: =C17-C9-C13 -> 15875
A33: Eco-Compensation : différence | C33: =C31-C32 -> 2800

Sheet DECOMPTE 2024
A3: 33689 - DECOMPTE GENERAL ANNEE 2024
A5: STRUCTURE | B5: PRESTATION | C5: MONTANT DU MARCHE HT | D5: DEJA FACTURE | E5: PREMIER ACOMPTE HT | F5: DEUXIEME ACOMPTE HT | G5: COMMENTAIRES
A6: ECO-COMPENSATION | B6: Pilotage et coordination | C6: =Planning!E32 -> 2425 | D6: 0 | E6: =C6*0.3 -> 727.5 | F6: =C6*0.7 -> 1697.5 | G6: -
A7: ECO-COMPENSATION | B7: Encadrement écologique | C7: 975 | D7: 0 | E7: =C7*0.3 -> 292.5 | F7: =-E7 -> -292.5 | G7: non réalisée
A8: ECO-COMPENSATION | C8: =SUM(C6:C7) -> 3400 | D8: 0 | E8: =E6+E7 -> 1020 | F8: =SUM(F6:F7) -> 1405 | G8: -
A9: SIMETHIS (SOUS-TRAITANT) | B9: Etat initial et suivis écologiques de l'espace de compensation | C9: =Planning!E37 -> 3375 | D9: 0 | E9: =C9*0.3 -> 1012.5 | F9: =C9*0.7 -> 2362.5 | G9: -
A10: SIMETHIS (SOUS-TRAITANT) | C10: =SUM(C9:C9) -> 3375 | D10: 0 | E10: =E9 -> 1012.5 | F10: =SUM(F9) -> 2362.5 | G10: -
A11: CERAG (SOUS-TRAITANT) | B11: Etat initial et suivis piézométriques, pédologiques et hydromorpholohiques de la zone humide compensatoire | C11: =Planning!E42 -> 2450 | D11: 0 | E11: =C11*0.3 -> 735 | F11: =C11*0.7 -> 1715 | G11: -
A12: CERAG (SOUS-TRAITANT) | C12: =SUM(C11:C11) -> 2450 | D12: 0 | E12: =E11 -> 735 | F12: =SUM(F11) -> 1715 | G12: -
A13: FACTURATION ECO-COMPENSATION | C13: =C8+C10+C12 -> 9225 | D13: =SUM(D8+D10+D12) -> 0 | E13: =E8+E10+E12 -> 2767.5 | F13: =SUM(F8+F10+F12) -> 5482.5 | G13: -
A15: EGAN Aquitaine (CO-TRAITANT) | B15: - | C15: 0 | D15: 0 | E15: 0 | F15: 0 | G15: Absence de travaux en 2024
A16: FACTURATION EGAN Aquitaine | C16: =SUM(C15:C15) -> 0 | D16: 0 | E16: 0 | F16: 0 | G16: 0
A18: TOTAL ANNEE 2024 | C18: MONTANT DU MARCHE HT | E18: TOTAL DÉJÀ FACTURE HT | F18: TOTAL FACTURE HT | G18: RESTANT A FACTURER TTC
A19: PREVISONNEL 2024 | C19: =C16+C13 -> 9225
A20: FIN DE MISSION 2024 | C20: =C19 -> 9225 | E20: =E13+E16 -> 2767.5 | F20: =F13 -> 5482.5 | G20: =(C20-E20-F20)*1.2 -> 1170

Sheet DECOMPTE 2025
A11: 33689 - DECOMPTE GENERAL ANNEE 2025
A13: STRUCTURE | B13: PRESTATION | C13: MONTANT DU MARCHE HT | D13: DEJA FACTURE | E13: PREMIER ACOMPTE HT | F13: DEUXIEME ACOMPTE HT | G13: COMMENTAIRES
A14: ECO-COMPENSATION | B14: Pilotage et coordination | C14: =Planning!E32 -> 2425 | D14: 0 | E14: =C14*0.3 -> 727.5 | F14: =C14*0.7 -> 1697.5 | G14: -
A15: ECO-COMPENSATION | C15: =SUM(C14:C14) -> 2425 | D15: 0 | E15: =SUM(E14) -> 727.5 | F15: =C15*0.7 -> 1697.5 | G15: -
A16: SIMETHIS (SOUS-TRAITANT) | B16: Etat initial et suivis écologiques de l'espace de compensation | C16: =Planning!E37 -> 3375 | D16: 0 | E16: =C16*0.3 -> 1012.5 | F16: =C16*0.7 -> 2362.5 | G16: -
A17: SIMETHIS (SOUS-TRAITANT) | C17: =SUM(C16:C16) -> 3375 | D17: 0 | E17: =E16 -> 1012.5 | F17: =C17*0.7 -> 2362.5 | G17: -
A18: CERAG (SOUS-TRAITANT) | B18: Etat initial et suivis piézométriques, pédologiques et hydromorpholohiques de la zone humide compensatoire | C18: =Planning!E42 -> 2450 | D18: 0 | E18: =C18*0.3 -> 735 | F18: =C18*0.7 -> 1715 | G18: -
A19: CERAG (SOUS-TRAITANT) | C19: =SUM(C18:C18) -> 2450 | D19: 0 | E19: =E18 -> 735 | F19: =C19*0.7 -> 1715 | G19: -
A20: FACTURATION ECO-COMPENSATION | C20: =C15+C17+C19 -> 8250 | D20: =SUM(D15+D17+D19) -> 0 | E20: =E15+E17+E19 -> 2475 | F20: =F15+F17+F19 -> 5775 | G20: -
A22: EGAN Aquitaine (CO-TRAITANT) | B22: - | C22: 0 | D22: 0 | E22: 0 | F22: 0 | G22: Absence de travaux en 2025
A23: FACTURATION EGAN Aquitaine | C23: =SUM(C22:C22) -> 0 | D23: 0 | E23: 0 | F23: 0 | G23: 0
A25: TOTAL ANNEE 2025 | C25: MONTANT DU MARCHE HT | E25: TOTAL DÉJÀ FACTURE HT | F25: FACTURE HT | G25: RESTANT A FACTURER TTC
A26: PREVISONNEL 2025 | C26: =C23+C20 -> 8250
A27: FIN DE MISSION 2025 | C27: =C26 -> 8250 | E27: =E20+E23 -> 2475 | F27: =F20 -> 5775 | G27: =(C27-E27-F27)*1.2 -> 0

Sheet DECOMPTE 2026
A11: 33689 - DECOMPTE GENERAL ANNEE 2026
A13: STRUCTURE | B13: PRESTATION | C13: MONTANT DU MARCHE HT | D13: DEJA FACTURE | E13: PREMIER ACOMPTE HT | F13: COMMENTAIRES
A14: ECO-COMPENSATION | B14: Pilotage et coordination | C14: =Planning!E32 -> 2425 | D14: 0 | E14: =C14*0.3 -> 727.5 | F14: -
A15: ECO-COMPENSATION | C15: =SUM(C14:C14) -> 2425 | D15: 0 | E15: =SUM(E14) -> 727.5 | F15: -
A16: SIMETHIS (SOUS-TRAITANT) | B16: Etat initial et suivis écologiques de l'espace de compensation | C16: =Planning!E37 -> 3375 | D16: 0 | E16: =C16*0.3 -> 1012.5 | F16: -
A17: SIMETHIS (SOUS-TRAITANT) | C17: =SUM(C16:C16) -> 3375 | D17: 0 | E17: =E16 -> 1012.5 | F17: -
A18: CERAG (SOUS-TRAITANT) | B18: Etat initial et suivis piézométriques, pédologiques et hydromorpholohiques de la zone humide compensatoire | C18: =Planning!E42 -> 2450 | D18: 0 | E18: =C18*0.3 -> 735 | F18: -
A19: CERAG (SOUS-TRAITANT) | C19: =SUM(C18:C18) -> 2450 | D19: 0 | E19: =E18 -> 735 | F19: -
A20: FACTURATION ECO-COMPENSATION | C20: =C15+C17+C19 -> 8250 | D20: =SUM(D15+D17+D19) -> 0 | E20: =E15+E17+E19 -> 2475 | F20: -
A22: EGAN Aquitaine (CO-TRAITANT) | B22: - | C22: 0 | D22: 0 | E22: 0 | F22: Absence de travaux en 2025
A23: FACTURATION EGAN Aquitaine | C23: =SUM(C22:C22) -> 0 | D23: 0 | E23: 0 | F23: 0
A25: TOTAL ANNEE 2026 | C25: MONTANT DU MARCHE HT | E25: FACTURE HT | F25: RESTANT A FACTURER TTC
A26: PREVISONNEL 2026 | C26: =C23+C20 -> 8250
A27: FIN DE MISSION 2026 | C27: =C26 -> 8250 | E27: =E20+E23 -> 2475 | F27: =(C27-E27)*1.2 -> 6930

Sheet PGZHC
D2: Etat de référence | E2: N | F2: N+1 | G2: N+2 | H2: N+3 | I2: N+4 | J2: N+5 | K2: N+6 | L2: N+7 | M2: N+8 | N2: N+9
A3: TRAVAUX DE GENIE ECOLOGIQUE | C3: Code mesure | D3: 2023 | E3: 2024 | F3: 2025 | G3: 2026 | H3: 2027 | I3: 2028 | J3: 2029 | K3: 2030 | L3: 2031 | M3: 2032 | N3: 2033
A4: Travaux de génie écologique (travaux uniques) | B4: Pose de 1 piézomètres incluant la maintance tous les 5 ans et le remplacement au bout de 15 ans | C4: SE 1 | D4: Réalisé | I4: Projeté | N4: Projeté
B5: Equipements des piézomètres avec des sondes et remplacement au bout de 10 ans | C5: SE 1 | D5: Réalisé | N5: Projeté
B6: Installation et repli de chantier inlaunt la mise en place d'un grillage à mouton | C6: - | D6: Réalisé
B7: Création de 2 dépressions humides par étrépage (50 cm) - environ 2 x 200 m² | C7: TU 1 | D7: Réalisé
B8: Création d'un seuil en rondins de bois | C8: TU 2 | D8: Mesure supprimée (absence d’effet notable + conflit d’usage)
B9: Suppression et évacuation des ligneux | C9: TU 3 | D9: Réalisé
A10: Travaux de génie écologique (travaux d'entretien) | B10: Entretien des landes humides | C10: TE 1 | D10: Réalisé | H10: Projeté | K10: Projeté | N10: Projeté
D12: N+10 | E12: N+11 | F12: N+12 | G12: N+13 | H12: N+14 | I12: N+15 | J12: N+16 | K12: N+17 | L12: N+18 | M12: N+19 | N12: N+20
A13: TRAVAUX DE GENIE ECOLOGIQUE | C13: Code mesure | D13: 2034 | E13: 2035 | F13: 2036 | G13: 2037 | H13: 2038 | I13: 2039 | J13: 2040 | K13: 2041 | L13: 2042 | M13: 2043 | N13: 2044
A14: Travaux de génie écologique (travaux uniques) | B14: Pose de 1 piézomètres incluant la maintance tous les 5 ans et le remplacement au bout de 15 ans | C14: SE 1 | H14: Projeté | M14: Projeté
B15: Equipements des piézomètres avec des sondes et remplacement au bout de 10 ans | C15: SE 1 | M15: Projeté
B16: Installation et repli de chantier inlaunt la mise en place d'un grillage à mouton | C16: -
B17: Création de 2 dépressions humides par étrépage (50 cm) - environ 2 x 200 m² | C17: TU 1
B18: Création d'un seuil en rondins de bois | C18: TU 2
B19: Suppression et évacuation des ligneux | C19: TU 3
A20: Travaux de génie écologique (travaux d'entretien) | B20: Entretien des landes humides | C20: TE 1 | F20: Projeté | I20: Projeté | L20: Projeté
D22: N+21 | E22: N+22 | F22: N+23 | G22: N+24 | H22: N+25 | I22: N+26 | J22: N+27 | K22: N+28 | L22: N+29
A23: TRAVAUX DE GENIE ECOLOGIQUE | C23: Code mesure | D23: 2045 | E23: 2046 | F23: 2047 | G23: 2048 | H23: 2049 | I23: 2050 | J23: 2051 | K23: 2052 | L23: 2053
A24: Travaux de génie écologique (travaux uniques) | B24: Pose de 1 piézomètres incluant la maintance tous les 5 ans et le remplacement au bout de 15 ans | C24: SE 1 | G24: Projeté
B25: Equipements des piézomètres avec des sondes et remplacement au bout de 10 ans | C25: SE 1
B26: Installation et repli de chantier inlaunt la mise en place d'un grillage à mouton | C26: -
B27: Création de 2 dépressions humides par étrépage (50 cm) - environ 2 x 200 m² | C27: TU 1
B28: Création d'un seuil en rondins de bois | C28: TU 2
B29: Suppression et évacuation des ligneux | C29: TU 3
A30: Travaux de génie écologique (travaux d'entretien) | B30: Entretien des landes humides | C30: TE 1 | D30: Projeté | G30: Projeté | J30: Projeté
